LICENSE
MANIFEST.in
README.rst
requirements.txt
setup.cfg
setup.py
certbot_aliyun_cdn/__init__.py
certbot_aliyun_cdn/aliyun_cdn.py
certbot_aliyun_cdn/client.py
certbot_aliyun_cdn.egg-info/PKG-INFO
certbot_aliyun_cdn.egg-info/SOURCES.txt
certbot_aliyun_cdn.egg-info/dependency_links.txt
certbot_aliyun_cdn.egg-info/entry_points.txt
certbot_aliyun_cdn.egg-info/requires.txt
certbot_aliyun_cdn.egg-info/top_level.txt
tests/requirements.txt